{
  "compressionlevel": -1,
  "height": 9,
  "infinite": false,
  "layers": [
    {
      "data": [
        1,
        3,
        3,
        3,
        3,
        3,
        3,
        3,
        3,
        1,
        11,
        13,
        13,
        16,
        16,
        16,
        16,
        13,
        16,
        22,
        24,
        26,
        26,
        26,
        26,
        0,
        0,
        26,
        26,
        33,
        26,
        0,
        0,
        0,
        0,
        0,
        0,
        0,
        0,
        0,
        26,
        0,
        0,
        0,
        41,
        41,
        41,
        0,
        0,
        0,
        0,
        0,
        0,
        41,
        41,
        41,
        0,
        0,
        0,
        0,
        0,
        0,
        0,
        0,
        0,
        0,
        0,
        0,
        0,
        0,
        0,
        0,
        0,
        0,
        0,
        0,
        0,
        0,
        0,
        0,
        0,
        0,
        0,
        0,
        53,
        54,
        0,
        0,
        0,
        0
      ],
      "height": 9,
      "id": 1,
      "name": "Ground",
      "opacity": 1,
      "type": "tilelayer",
      "visible": true,
      "width": 10,
      "x": 0,
      "y": 0
    },
    {
      "data": [
        2,
        4,
        5,
        6,
        7,
        8,
        8,
        9,
        8,
        10,
        12,
        14,
        15,
        17,
        18,
        19,
        19,
        20,
        21,
        23,
        25,
        27,
        28,
        29,
        30,
        26,
        26,
        31,
        32,
        34,
        35,
        36,
        37,
        37,
        37,
        37,
        37,
        37,
        38,
        39,
        35,
        40,
        41,
        41,
        42,
        43,
        44,
        41,
        45,
        39,
        26,
        40,
        41,
        46,
        47,
        48,
        41,
        41,
        45,
        39,
        26,
        49,
        50,
        50,
        50,
        50,
        50,
        50,
        51,
        39,
        26,
        39,
        39,
        39,
        39,
        39,
        39,
        39,
        39,
        39,
        26,
        39,
        39,
        39,
        19,
        19,
        39,
        39,
        39,
        39
      ],
      "height": 9,
      "id": 2,
      "name": "Objects",
      "opacity": 1,
      "type": "tilelayer",
      "visible": true,
      "width": 10,
      "x": 0,
      "y": 0
    },
    {
      "data": [
        0,
        0,
        0,
        0,
        0,
        0,
        0,
        0,
        0,
        0,
        0,
        0,
        0,
        0,
        0,
        0,
        0,
        0,
        0,
        0,
        0,
        0,
        0,
        0,
        0,
        19,
        19,
        0,
        0,
        0,
        0,
        19,
        19,
        19,
        19,
        19,
        19,
        19,
        19,
        19,
        0,
        19,
        19,
        19,
        0,
        0,
        0,
        19,
        19,
        19,
        19,
        19,
        19,
        0,
        0,
        0,
        19,
        19,
        19,
        19,
        19,
        19,
        19,
        19,
        19,
        19,
        19,
        19,
        19,
        19,
        19,
        19,
        19,
        19,
        19,
        19,
        19,
        19,
        19,
        19,
        52,
        19,
        19,
        19,
        0,
        0,
        19,
        19,
        19,
        55
      ],
      "height": 9,
      "id": 3,
      "name": "Overhead",
      "opacity": 1,
      "type": "tilelayer",
      "visible": true,
      "width": 10,
      "x": 0,
      "y": 0
    },
    {
      "id": 4,
      "name": "Warps",
      "type": "objectgroup",
      "visible": true,
      "opacity": 1,
      "x": 0,
      "y": 0,
      "objects": [
        {
          "id": 1,
          "name": "Warp to pacifidlog_town",
          "type": "warp_event",
          "x": 64,
          "y": 128,
          "width": 16,
          "height": 16,
          "properties": [
            {
              "name": "warp",
              "propertytype": "Warp",
              "type": "class",
              "value": {
                "map": "base:map:hoenn/pacifidlog_town",
                "x": 2,
                "y": 12
              }
            },
            {
              "name": "elevation",
              "type": "int",
              "value": 0
            }
          ]
        },
        {
          "id": 2,
          "name": "Warp to pacifidlog_town",
          "type": "warp_event",
          "x": 80,
          "y": 128,
          "width": 16,
          "height": 16,
          "properties": [
            {
              "name": "warp",
              "propertytype": "Warp",
              "type": "class",
              "value": {
                "map": "base:map:hoenn/pacifidlog_town",
                "x": 2,
                "y": 12
              }
            },
            {
              "name": "elevation",
              "type": "int",
              "value": 0
            }
          ]
        }
      ]
    },
    {
      "id": 5,
      "name": "NPCs",
      "type": "objectgroup",
      "visible": true,
      "opacity": 1,
      "x": 0,
      "y": 0,
      "objects": [
        {
          "id": 3,
          "name": "NPC_3",
          "type": "npc",
          "x": 48,
          "y": 64,
          "width": 16,
          "height": 16,
          "visible": true,
          "properties": [
            {
              "name": "spriteId",
              "type": "string",
              "value": "base:sprite:npcs/generic/woman_2"
            },
            {
              "name": "behaviorId",
              "type": "string",
              "value": "base:behavior:movement/stationary"
            },
            {
              "name": "elevation",
              "type": "int",
              "value": 3
            },
            {
              "name": "direction",
              "type": "string",
              "value": "down"
            },
            {
              "name": "interactionId",
              "type": "string",
              "value": "base:behavior:interaction/pacifidlog_town_house4_event_script_woman"
            }
          ]
        },
        {
          "id": 4,
          "name": "NPC_4",
          "type": "npc",
          "x": 112,
          "y": 80,
          "width": 16,
          "height": 16,
          "visible": true,
          "properties": [
            {
              "name": "spriteId",
              "type": "string",
              "value": "base:sprite:npcs/generic/little_girl"
            },
            {
              "name": "behaviorId",
              "type": "string",
              "value": "base:behavior:movement/wander"
            },
            {
              "name": "elevation",
              "type": "int",
              "value": 3
            },
            {
              "name": "rangeX",
              "type": "int",
              "value": 1
            },
            {
              "name": "rangeY",
              "type": "int",
              "value": 1
            },
            {
              "name": "interactionId",
              "type": "string",
              "value": "base:behavior:interaction/pacifidlog_town_house4_event_script_little_girl"
            }
          ]
        },
        {
          "id": 5,
          "name": "NPC_5",
          "type": "npc",
          "x": 112,
          "y": 64,
          "width": 16,
          "height": 16,
          "visible": true,
          "properties": [
            {
              "name": "spriteId",
              "type": "string",
              "value": "base:sprite:npcs/generic/boy_1"
            },
            {
              "name": "behaviorId",
              "type": "string",
              "value": "base:behavior:movement/wander"
            },
            {
              "name": "elevation",
              "type": "int",
              "value": 3
            },
            {
              "name": "rangeX",
              "type": "int",
              "value": 1
            },
            {
              "name": "rangeY",
              "type": "int",
              "value": 1
            },
            {
              "name": "interactionId",
              "type": "string",
              "value": "base:behavior:interaction/pacifidlog_town_house4_event_script_boy"
            }
          ]
        }
      ]
    }
  ],
  "nextlayerid": 1,
  "nextobjectid": 6,
  "orientation": "orthogonal",
  "renderorder": "right-down",
  "tiledversion": "1.11.2",
  "tileheight": 16,
  "tilewidth": 16,
  "type": "map",
  "version": "1.11",
  "width": 10,
  "properties": [
    {
      "name": "display_name",
      "type": "string",
      "value": "PacifidlogTown_House4"
    },
    {
      "name": "region",
      "type": "string",
      "value": "Hoenn"
    },
    {
      "name": "weather",
      "type": "string",
      "value": "WEATHER_NONE"
    },
    {
      "name": "mapType",
      "type": "string",
      "value": "MAP_TYPE_INDOOR"
    },
    {
      "name": "showMapName",
      "type": "bool",
      "value": false
    },
    {
      "name": "requiresFlash",
      "type": "bool",
      "value": false
    },
    {
      "name": "allowCycling",
      "type": "bool",
      "value": false
    },
    {
      "name": "allowEscaping",
      "type": "bool",
      "value": false
    },
    {
      "name": "allowRunning",
      "type": "bool",
      "value": false
    },
    {
      "name": "battleScene",
      "type": "string",
      "value": "MAP_BATTLE_SCENE_NORMAL"
    },
    {
      "name": "music",
      "type": "string",
      "value": "base:audio:music/towns/mus_lilycove"
    },
    {
      "name": "regionMapSection",
      "type": "string",
      "value": "base:mapsec:hoenn/pacifidlog_town"
    },
    {
      "name": "border",
      "propertytype": "Border",
      "type": "class",
      "value": {
        "top_left": 1,
        "top_right": 1,
        "bottom_left": 1,
        "bottom_right": 1,
        "top_left_top": 19,
        "top_right_top": 19,
        "bottom_left_top": 19,
        "bottom_right_top": 19
      }
    }
  ],
  "tilesets": [
    {
      "firstgid": 1,
      "source": "../../../Tilesets/hoenn/pacifidlog_town_house4/pacifidlog_town_house4.json"
    }
  ]
}